mappings/DatasetOrganisation.py
mappings/DatasetOrganisationNormalise.py
mappings/Merger.py
mappings/NetworkasDiGraph.py
mappings/RandomTrail.py
mappings/TrailsAnalysis.py
mappings/__main__.py
mappings/getFoldChangeCDF.py
mappings/data/input/NetworkComplete.csv
mappings/data/input/sampleData_PFalciparumTrophozoiteStage.csv
mappings-0.0.4.dist-info/LICENSE
mappings-0.0.4.dist-info/METADATA
mappings-0.0.4.dist-info/WHEEL
mappings-0.0.4.dist-info/entry_points.txt
mappings-0.0.4.dist-info/top_level.txt
mappings-0.0.4.dist-info/RECORD
