Metadata-Version: 2.1
Name: mappings
Version: 0.0.4
Summary: Mapping and Analysis of Phosphorylation Pathways Identified through Network/Graph Signalling
Home-page: https://github.com/finnod/mappings
Author: Finn O'Donoghue
Author-email: finnodonoghue@gmail.com
License: UNKNOWN
Keywords: mapping,analysis,phosphorylation,pathways,network,graph,signalling,kinase,kinases,kinexus,protein,informatics,bioinformatics
Platform: UNKNOWN
Classifier: Development Status :: 2 - Pre-Alpha
Classifier: Environment :: Console
Classifier: Topic :: Scientific/Engineering :: Bio-Informatics
Classifier: Topic :: Scientific/Engineering :: Information Analysis
Classifier: Topic :: Scientific/Engineering :: Mathematics
Classifier: Intended Audience :: End Users/Desktop
Classifier: Operating System :: MacOS :: MacOS X
Classifier: Operating System :: Microsoft :: Windows
Classifier: Operating System :: POSIX
Classifier: Programming Language :: Python
License-File: LICENSE
Requires-Dist: numpy
Requires-Dist: pandas
Requires-Dist: click
Requires-Dist: pathlib
Requires-Dist: networkx
Requires-Dist: tqdm
